LICENSE
README.md
setup.py
departments/__init__.py
departments/admin.py
departments/apps.py
departments/models.py
departments/tests.py
departments/views.py
departments/forms/__init__.py
departments/forms/forms.py
departments/migrations/0001_initial.py
departments/migrations/0002_alter_department_unique_together_department_path_and_more.py
departments/migrations/__init__.py
departments/views/__init__.py
departments/views/department.py
django_simple_department.egg-info/PKG-INFO
django_simple_department.egg-info/SOURCES.txt
django_simple_department.egg-info/dependency_links.txt
django_simple_department.egg-info/top_level.txt