Metadata-Version: 2.1
Name: django-simple-department
Version: 0.1.1
Summary: 一个测试的包
Author: yuwenyang
Author-email: ywyhpnn@126.com
License: UNKNOWN
Platform: UNKNOWN
Classifier: Programming Language :: Python :: 3
Requires-Python: >=3
License-File: LICENSE
